pyvene/__init__.py
pyvene/analyses/visualization.py
pyvene/data_generators/__init__.py
pyvene/data_generators/causal_model.py
pyvene/models/__init__.py
pyvene/models/basic_utils.py
pyvene/models/configuration_intervenable_model.py
pyvene/models/constants.py
pyvene/models/intervenable_base.py
pyvene/models/intervenable_modelcard.py
pyvene/models/intervention_utils.py
pyvene/models/interventions.py
pyvene/models/layers.py
pyvene/models/modeling_utils.py
pyvene/models/backpack_gpt2/__init__.py
pyvene/models/backpack_gpt2/modelings_backpack_gpt2.py
pyvene/models/backpack_gpt2/modelings_intervenable_backpack_gpt2.py
pyvene/models/blip/__init__.py
pyvene/models/blip/modelings_blip.py
pyvene/models/blip/modelings_blip_itm.py
pyvene/models/blip/modelings_intervenable_blip.py
pyvene/models/blip/modelings_intervenable_blip_itm.py
pyvene/models/esm/__init__.py
pyvene/models/esm/modelings_intervenable_esm.py
pyvene/models/gemma/__init__.py
pyvene/models/gemma/modelings_intervenable_gemma.py
pyvene/models/gemma2/__init__.py
pyvene/models/gemma2/modelings_intervenable_gemma2.py
pyvene/models/gpt2/__init__.py
pyvene/models/gpt2/modelings_intervenable_gpt2.py
pyvene/models/gpt_neo/__init__.py
pyvene/models/gpt_neo/modelings_intervenable_gpt_neo.py
pyvene/models/gpt_neox/__init__.py
pyvene/models/gpt_neox/modelings_intervenable_gpt_neox.py
pyvene/models/gru/__init__.py
pyvene/models/gru/modelings_gru.py
pyvene/models/gru/modelings_intervenable_gru.py
pyvene/models/llama/__init__.py
pyvene/models/llama/modelings_intervenable_llama.py
pyvene/models/llava/__init__.py
pyvene/models/llava/modelings_intervenable_llava.py
pyvene/models/mistral/__init__.py
pyvene/models/mistral/modellings_intervenable_mistral.py
pyvene/models/mlp/__init__.py
pyvene/models/mlp/modelings_intervenable_mlp.py
pyvene/models/mlp/modelings_mlp.py
pyvene/models/olmo/__init__.py
pyvene/models/olmo/modelings_intervenable_olmo.py
pyvene/models/qwen2/__init__.py
pyvene/models/qwen2/modelings_intervenable_qwen2.py
pyvene-0.1.8.dist-info/METADATA
pyvene-0.1.8.dist-info/WHEEL
pyvene-0.1.8.dist-info/licenses/LICENSE
pyvene-0.1.8.dist-info/RECORD
