Metadata-Version: 2.4
Name: pyvene
Version: 0.1.8
Summary: Use Activation Intervention to Interpret Causal Mechanism of Model
Project-URL: Documentation, https://stanfordnlp.github.io/pyvene
Project-URL: Homepage, https://github.com/stanfordnlp/pyvene
Project-URL: Repository, https://github.com/stanfordnlp/pyvene.git
Author-email: Zhengxuan Wu <wuzhengx@stanford.edu>
License: Apache License 2.0
License-File: LICENSE
Classifier: Development Status :: 3 - Alpha
Classifier: Intended Audience :: Science/Research
Classifier: License :: OSI Approved :: Apache Software License
Classifier: Operating System :: POSIX :: Linux
Classifier: Programming Language :: Python :: 3
Classifier: Programming Language :: Python :: 3.9
Requires-Python: >=3.9
Requires-Dist: accelerate>=0.34.2
Requires-Dist: datasets>=3.0.1
Requires-Dist: fsspec>=2023.6.0
Requires-Dist: huggingface-hub>=0.25.1
Requires-Dist: ipywidgets>=8.1.1
Requires-Dist: matplotlib>=3.7.4
Requires-Dist: numpy>1.24.4
Requires-Dist: plotnine>=0.12.4
Requires-Dist: protobuf>=3.20.0
Requires-Dist: sentencepiece>=0.2.0
Requires-Dist: tokenizers>=0.20.0
Requires-Dist: torch>=2.0.0
Requires-Dist: transformers>=4.45.1
